{
  "$schema": "https://mintlify.com/docs.json",
  "name": "SIC-HVD",
  "theme": "almond",
  "colors": {
    "primary": "#fc2c24",
    "light": "#040404",
    "dark": "#e29d78"
  },
  "favicon": "https://media.brand.dev/55480c38-4203-413d-8622-69e15c7b6ed1.jpg",
  "logo": {
    "light": "https://media.brand.dev/a38501a7-458d-4f61-8fc0-8bd969c561f8.svg",
    "dark": "https://media.brand.dev/a38501a7-458d-4f61-8fc0-8bd969c561f8.svg"
  },
  "navbar": {
    "primary": {
      "type": "github",
      "href": "https://github.com/it-hvd/sic-hvd"
    }
  },
  "footer": {
    "socials": {
      "github": "https://github.com/it-hvd/sic-hvd"
    }
  },
  "navigation": {
    "tabs": [
      {
        "tab": "Getting Started",
        "groups": [
          {
            "group": "Overview",
            "pages": ["introduction", "getting-started/quickstart"]
          },
          {
            "group": "Deployment",
            "pages": [
              "getting-started/installation",
              "getting-started/docker-deployment",
              "getting-started/environment-configuration"
            ]
          }
        ]
      },
      {
        "tab": "User Guide",
        "groups": [
          {
            "group": "Requests",
            "pages": [
              "user-guide/capital-investment-requests",
              "user-guide/memo-requests",
              "user-guide/attachments-and-options"
            ]
          },
          {
            "group": "Approval Workflow",
            "pages": [
              "user-guide/approval-workflow",
              "user-guide/roles-and-permissions",
              "user-guide/notifications"
            ]
          },
          {
            "group": "Administration",
            "pages": [
              "user-guide/user-management",
              "user-guide/company-department-management",
              "user-guide/dashboard-and-reports"
            ]
          }
        ]
      },
      {
        "tab": "Technical Reference",
        "groups": [
          {
            "group": "Architecture",
            "pages": [
              "reference/architecture-overview",
              "reference/data-models",
              "reference/request-statuses"
            ]
          },
          {
            "group": "Configuration",
            "pages": [
              "reference/filament-panel",
              "reference/mail-and-notifications",
              "reference/pdf-export"
            ]
          }
        ]
      }
    ]
  }
}
